mysqlrocket/__init__.py
mysqlrocket/mysqlrocket.py
mysqlrocket/ressources.py
mysqlrocket-0.3.1.dist-info/DESCRIPTION.rst
mysqlrocket-0.3.1.dist-info/METADATA
mysqlrocket-0.3.1.dist-info/RECORD
mysqlrocket-0.3.1.dist-info/WHEEL
mysqlrocket-0.3.1.dist-info/entry_points.txt
mysqlrocket-0.3.1.dist-info/metadata.json
mysqlrocket-0.3.1.dist-info/top_level.txt
