Metadata-Version: 2.0
Name: mysqlrocket
Version: 0.3.1
Summary: Simple CLI tool to create and delete easily MySQL databases.
Home-page: https://github.com/cypx/mysqlrocket
Author: Cyprien Devillez
Author-email: cyp@bidouille.info
License: GPL
Platform: UNKNOWN
Classifier: Programming Language :: Python
Classifier: License :: OSI Approved
Classifier: Natural Language :: English
Classifier: Operating System :: OS Independent
Classifier: Programming Language :: Python :: 2.6
Classifier: Programming Language :: Python :: 2.7
Classifier: Programming Language :: Python :: 3.4
Classifier: Programming Language :: Python :: 3.5
Classifier: Programming Language :: Python :: 3.6
Classifier: Topic :: Database
Classifier: Topic :: Utilities
Classifier: Development Status :: 4 - Beta
Requires-Dist: appdirs
Requires-Dist: argparse
Requires-Dist: configparser; python_version < "3"
Requires-Dist: future; python_version < "3"
Requires-Dist: MySQL-python; python_version < "3"
Requires-Dist: mysqlclient; python_version >= "3"
